setup.py
funnytest/__init__.py
funnytest.egg-info/PKG-INFO
funnytest.egg-info/SOURCES.txt
funnytest.egg-info/dependency_links.txt
funnytest.egg-info/not-zip-safe
funnytest.egg-info/top_level.txt