Metadata-Version: 1.0
Name: funnytest
Version: 0.1
Summary: The funnytest is something
Home-page: UNKNOWN
Author: Yank Lu
Author-email: yanklu@gmail.com
License: MIT
Platform: UNKNOWN
